nonebot_plugin_exdi-0.1.8.dist-info/METADATA
nonebot_plugin_exdi-0.1.8.dist-info/WHEEL
nonebot_plugin_exdi-0.1.8.dist-info/entry_points.txt
nonebot_plugin_exdi-0.1.8.dist-info/licenses/LICENSE
nonebot_plugin_exdi/__init__.py
nonebot_plugin_exdi/baseparams.py
nonebot_plugin_exdi/config.py
nonebot_plugin_exdi/dependent.py
nonebot_plugin_exdi/di.py
nonebot_plugin_exdi/overwrite.py
nonebot_plugin_exdi/params.py
nonebot_plugin_exdi-0.1.8.dist-info/RECORD
