Metadata-Version: 2.1
Name: nonebot-plugin-exdi
Version: 0.1.8
Summary: 依赖注入扩展,允许对非handle函数进行依赖注入
Author-Email: "Mr.Lee" <chzxxuanzheng@gmail.com>
License: GPLv3
Requires-Python: >=3.10
Requires-Dist: anyio>=4.4.0
Requires-Dist: exceptiongroup>=1.2.2
Requires-Dist: nonebot2>=2.4.2
